{
  "_id": "80d767adf8abb3a6",
  "_key": "!items!80d767adf8abb3a6",
  "name": "Major Image",
  "type": "spell",
  "img": "icons/svg/item-bag.svg",
  "system": {
    "description": "<p>This spell creates the illusion of an object, creature, or force, as visualized by the caster. Sound, smell, and thermal illusions are all within the spells power to create. Creatures who view the illusion believe it, and can suffer damage from illusions. Hit point damage is suffered from damage to the mind/psyche. While concentrating, the caster can move the image within the range. The image persists for 3 rounds after the caster ceases concentrating. The image disappears if an opponent makes the saving throw. The spell affects a 40 cubic foot area + 10 cubic feet per level.</p>",
    "class": {
      "value": "Illusionist",
      "label": "TLGCC.Class"
    },
    "duration": {
      "value": "see below",
      "label": "TLGCC.Duration"
    },
    "savevalue": {
      "value": "intelligence (disbelief)",
      "label": "TLGCC.SaveValue"
    },
    "spellresist": {
      "value": "no",
      "label": "TLGCC.SpellResistance"
    },
    "spellcomp": {
      "value": "V, S",
      "label": "TLGCC.SpellComp"
    },
    "prepared": {
      "value": 0,
      "label": "TLGCC.Prepared"
    },
    "range": {
      "value": "450 ft.",
      "label": "TLGCC.Range"
    },
    "spelldmg": {
      "value": "",
      "label": "TLGCC.SpellDamage"
    },
    "cast": {
      "value": "1",
      "label": "TLGCC.SpellCastTime"
    },
    "component": {
      "value": "",
      "label": "TLGCC.SpellComponent"
    },
    "summary": {
      "value": "",
      "label": "TLGCC.SpellSummary"
    },
    "spellLevel": {
      "value": 3,
      "label": "TLGCC.SpellLevel"
    },
    "spell": {
      "spelllevel": 3,
      "summary": ""
    }
  },
  "effects": [],
  "folder": "0989ad6c26833a69",
  "flags": {},
  "ownership": {
    "default": 0
  }
}
